shimexpy_gui/__init__.py
shimexpy_gui/app.py
shimexpy_gui/config.py
shimexpy_gui/image_processor.py
shimexpy_gui/image_widget.py
shimexpy_gui/mainwindow.py
shimexpy_gui/assets/style.qss
shimexpy_gui-0.1.0.dist-info/METADATA
shimexpy_gui-0.1.0.dist-info/WHEEL
shimexpy_gui-0.1.0.dist-info/entry_points.txt
shimexpy_gui-0.1.0.dist-info/top_level.txt
shimexpy_gui-0.1.0.dist-info/RECORD
